[{"id": 520575530143251, "advertiser_name": "Z.K. Harlow Excavating LLC", "status": "Active", "date": "01/27/2023", "ad_url": ["https://www.facebook.com/people/ZK-Harlow-Excavating-LLC/100057295485950/"], "image_save_path": ["520575530143251_00.jpg"], "ad_text": "Z.K. Harlow Excavating LLC Sponsored We are consistently booking work for this upcoming seasons and we have a few positions we are looking to fill. If you or anyone you know is interested in any of the positions listed below give us a call at 317-560-0123 \u2022Class A CDL truck driver/ laborer \u2022Underground utility excavation operator \u2022Concrete crew, preferably a foreman with experience in flat work that can assist to put together a crew of skilled finishers, or an established crew that is interested in subcontracting for Z.K. Harlow Excavating LLC Z.K. Harlow Excavating LLC Licensed, bonded, and insured excavation company here to tackle any and all of your projects needs. Call Now", "grouping_count": 0}]