[{"id": 1635764470202636, "advertiser_name": "Energy Transportation, LLC", "status": "Active", "date": "01/18/2023", "ad_url": [], "image_save_path": ["1635764470202636_00.jpg"], "ad_text": "Energy Transportation, LLC Sponsored Competitive Benefit Plans (Health, Dental,Vision Short and Long term Disability Company paid Life Insurance Paid vacation and Holidays Day and Night Shift available Minimum 2 years CDL Class A or B Tanker Endorsement Required 50-60 hours a week Earnings Potential: Up to 100,000+ FULL-TIME \u00b7 BRIDGEPORT, WEST VIRGINIA Water Truck Driver Apply now", "grouping_count": 0}]