[{"id": 519179413535570, "advertiser_name": "South Coast Carriers", "status": "Active", "date": "01/26/2023", "ad_url": [], "image_save_path": ["519179413535570_00.jpg"], "ad_text": "South Coast Carriers Sponsored We are looking for full-time CDL Class A drivers for 48' flatbed positions. - Opportunity to earn between $66,000 to $95,000/year - Hourly pay - 1-2 nights out of town per week - Home on weekends - Monday - Friday schedule with an AM start - Weekly pay by direct deposit - 50-70 hours per week - Assigned truck FULL-TIME \u00b7 $23 - $28 / HOUR \u00b7 HUMBLE, TEXAS Class A CDL Truck Driver Apply now", "grouping_count": 0}]