[{"id": 1531460790667664, "advertiser_name": "Ascension St. Vincent's Alabama", "status": "Active", "date": "01/11/2023", "ad_url": [], "image_save_path": [], "ad_text": "Ascension St. Vincent's Alabama Sponsored Because we're unable to determine your age, we cannot show you this ad.", "grouping_count": 0}, {"id": 1317329045787604, "advertiser_name": "Ascension St. Vincent's Alabama", "status": "Active", "date": "01/06/2023", "ad_url": [], "image_save_path": [], "ad_text": "Ascension St. Vincent's Alabama Sponsored Because we're unable to determine your age, we cannot show you this ad.", "grouping_count": 0}]