[{"id": 1124177268271512, "advertiser_name": "W & W Truck & Tractor", "status": "Active", "date": "01/05/2023", "ad_url": ["https://l.facebook.com/l.php?u=http%3A%2F%2Fwww.wwtractor.com%2F&h=AT2vXSrZM1X86jGeThjzkOTf1IGY9HsKzy0ZUXXjP7wWwy_vh6Ez_IhkKZSOtcf_FgUL8oOj7E2GGKx1RA8EsdV9N27BbbXadiTQIitwVO6llx16H0404bRIc5LeXkUVisYJIY_19rIvXJzu8ACAycElnYZtwFCPFWf1zjFEH3o"], "image_save_path": ["1124177268271512_00.jpg"], "ad_text": "W & W Truck & Tractor Sponsored We are looking for employees to assist in our heavy equipment dismantling business. The position is full time Monday \u2013 Friday 8am to 5pm with breaks throughout the day. We offer competitive pay and full benefits after a probationary period (free uniforms, sick pay, vacation pay, holiday pay, employer provided - health insurance, eye and dental, and retirement). We are a local third generation family owned business that has operated for 50 years in Berkeley County. Must have a valid SC driver's license and have dependable transportation to work. WWTRACTOR.COM We are hiring! W & W Truck & Tractor Inc. Apply now", "grouping_count": 0}]